imblearn_extra/__init__.py
imblearn_extra/clover/__init__.py
imblearn_extra/clover/clusterer/__init__.py
imblearn_extra/clover/clusterer/_som.py
imblearn_extra/clover/distribution/__init__.py
imblearn_extra/clover/distribution/_density.py
imblearn_extra/clover/distribution/base.py
imblearn_extra/clover/over_sampling/__init__.py
imblearn_extra/clover/over_sampling/_cluster.py
imblearn_extra/clover/over_sampling/_gsomo.py
imblearn_extra/clover/over_sampling/_kmeans_smote.py
imblearn_extra/clover/over_sampling/_somo.py
imblearn_extra/gsmote/__init__.py
imblearn_extra/gsmote/geometric_smote.py
imblearn_extra/py.typed
imbalanced_learn_extra-0.7.0.dist-info/WHEEL
imbalanced_learn_extra-0.7.0.dist-info/METADATA
imbalanced_learn_extra-0.7.0.dist-info/licenses/LICENSE
imbalanced_learn_extra-0.7.0.dist-info/RECORD
