Metadata-Version: 2.1
Name: imbalanced-learn-extra
Version: 0.7.0
Summary: An implementation of novel oversampling algorithms.
License: MIT
Keywords: machine learning,imbalanced learning,oversampling
Author-email: Georgios Douzas <gdouzas@icloud.com>
Requires-Python: >=3.10, <3.13
Classifier: Development Status :: 4 - Beta
Classifier: Intended Audience :: Developers
Classifier: Programming Language :: Python
Classifier: Programming Language :: Python :: 3
Classifier: Programming Language :: Python :: 3 :: Only
Classifier: Programming Language :: Python :: 3.10
Classifier: Programming Language :: Python :: 3.11
Classifier: Programming Language :: Python :: 3.12
Classifier: Topic :: Documentation
Classifier: Topic :: Software Development
Classifier: Topic :: Utilities
Classifier: Typing :: Typed
Requires-Dist: MiniSom>=2.3.2
Requires-Dist: imbalanced-learn>=0.11.0
Requires-Dist: numpy>=1.22
Requires-Dist: scikit-learn>=1.3.2
Requires-Dist: scipy>=1.7.2
Requires-Dist: typing-extensions>=4.8.0
Project-URL: Changelog, https://georgedouzas.github.io/imbalanced-learn-extra/changelog
Project-URL: Discussions, https://github.com/georgedouzas/imbalanced-learn-extra/discussions
Project-URL: Documentation, https://georgedouzas.github.io/imbalanced-learn-extra
Project-URL: Funding, https://github.com/sponsors/georgedouzas
Project-URL: Gitter, https://gitter.im/imbalanced-learn-extra/community
Project-URL: Homepage, https://georgedouzas.github.io/imbalanced-learn-extra
Project-URL: Issues, https://github.com/georgedouzas/imbalanced-learn-extra/issues
Project-URL: Repository, https://github.com/georgedouzas/imbalanced-learn-extra
